{"date":"2026-04-26","snapshots":[{"timestamp":1777161653,"aircraft":[]},{"timestamp":1777161941,"aircraft":[{"icao24":"ae1464","callsign":"RCH122","country":"USA","lat":49.826139,"lon":12.345271,"altitude":8229.6,"velocity":250.534228,"heading":102,"on_ground":false}]},{"timestamp":1777162241,"aircraft":[{"icao24":"ae1464","callsign":"RCH122","country":"USA","lat":49.629023,"lon":13.357539,"altitude":8229.6,"velocity":259.279776,"heading":106,"on_ground":false}]},{"timestamp":1777162541,"aircraft":[{"icao24":"ae1464","callsign":"RCH122","country":"USA","lat":49.416384,"lon":14.359497,"altitude":8221.98,"velocity":254.64978,"heading":109,"on_ground":false}]},{"timestamp":1777162841,"aircraft":[{"icao24":"ae1464","callsign":"RCH122","country":"USA","lat":49.192243,"lon":15.363081,"altitude":8229.6,"velocity":259.279776,"heading":110,"on_ground":false}]},{"timestamp":1777163138,"aircraft":[{"icao24":"ae1464","callsign":"RCH122","country":"USA","lat":48.960961,"lon":16.348556,"altitude":8229.6,"velocity":257.736444,"heading":110,"on_ground":false}]},{"timestamp":1777163450,"aircraft":[]},{"timestamp":1777163739,"aircraft":[{"icao24":"ae1464","callsign":"RCH122","country":"USA","lat":48.232713,"lon":18.114766,"altitude":8221.98,"velocity":255.16422400000002,"heading":136,"on_ground":false}]},{"timestamp":1777164041,"aircraft":[]},{"timestamp":1777164340,"aircraft":[]},{"timestamp":1777164640,"aircraft":[{"icao24":"ae2faa","callsign":"RCH525","country":"USA","lat":48.244629,"lon":19.018531,"altitude":10972.800000000001,"velocity":209.1729304,"heading":306,"on_ground":false}]},{"timestamp":1777164940,"aircraft":[{"icao24":"ae2faa","callsign":"RCH525","country":"USA","lat":48.573443,"lon":18.332929,"altitude":10972.800000000001,"velocity":207.578154,"heading":305.62,"on_ground":false}]},{"timestamp":1777165242,"aircraft":[{"icao24":"ae2faa","callsign":"RCH525","country":"USA","lat":48.891541,"lon":17.631437,"altitude":10972.800000000001,"velocity":209.5844856,"heading":296.69,"on_ground":false}]},{"timestamp":1777165539,"aircraft":[{"icao24":"ae2faa","callsign":"RCH525","country":"USA","lat":49.120239,"lon":16.862323,"altitude":10972.800000000001,"velocity":204.1313792,"heading":291.59,"on_ground":false}]},{"timestamp":1777165839,"aircraft":[{"icao24":"ae2faa","callsign":"RCH525","country":"USA","lat":49.319489,"lon":16.087598,"altitude":10302.24,"velocity":205.67471120000002,"heading":291.11,"on_ground":false}]},{"timestamp":1777166141,"aircraft":[{"icao24":"ae2faa","callsign":"RCH525","country":"USA","lat":49.51973,"lon":15.280103,"altitude":9753.6,"velocity":213.28848240000002,"heading":290.62,"on_ground":false}]},{"timestamp":1777166440,"aircraft":[{"icao24":"ae2faa","callsign":"RCH525","country":"USA","lat":49.718719,"lon":14.450635,"altitude":9753.6,"velocity":215.60348040000002,"heading":289.95,"on_ground":false}]},{"timestamp":1777166739,"aircraft":[{"icao24":"ae2faa","callsign":"RCH525","country":"USA","lat":49.912984,"lon":13.606939,"altitude":9753.6,"velocity":215.2433696,"heading":289.26,"on_ground":false}]},{"timestamp":1777167044,"aircraft":[{"icao24":"ae2faa","callsign":"RCH525","country":"USA","lat":50.104935,"lon":12.738358,"altitude":9753.6,"velocity":219.7704768,"heading":288.56,"on_ground":false}]},{"timestamp":1777167338,"aircraft":[{"icao24":"ae146f","callsign":"RCH652","country":"USA","lat":49.424703,"lon":12.743505,"altitude":8229.6,"velocity":246.418676,"heading":101,"on_ground":false}]},{"timestamp":1777167640,"aircraft":[{"icao24":"ae146f","callsign":"RCH652","country":"USA","lat":49.29621,"lon":13.714805,"altitude":8229.6,"velocity":239.730904,"heading":102,"on_ground":false}]},{"timestamp":1777167940,"aircraft":[{"icao24":"ae1235","callsign":"RCH694","country":"USA","lat":49.390827,"lon":12.947688,"altitude":9448.800000000001,"velocity":246.93312,"heading":101.07,"on_ground":false},{"icao24":"ae146f","callsign":"RCH652","country":"USA","lat":49.155568,"lon":14.7135,"altitude":8229.6,"velocity":258.25088800000003,"heading":101,"on_ground":false},{"icao24":"ae0677","callsign":"MOOSE43","country":"USA","lat":48.15539,"lon":18.775296,"altitude":10972.800000000001,"velocity":197.032052,"heading":315,"on_ground":false}]},{"timestamp":1777168240,"aircraft":[{"icao24":"ae1235","callsign":"RCH694","country":"USA","lat":49.256853,"lon":13.959575,"altitude":9448.800000000001,"velocity":248.990896,"heading":101.78,"on_ground":false},{"icao24":"ae146f","callsign":"RCH652","country":"USA","lat":48.997202,"lon":15.760811,"altitude":8229.6,"velocity":257.222,"heading":102,"on_ground":false},{"icao24":"ae0677","callsign":"MOOSE43","country":"USA","lat":48.530437,"lon":18.218261,"altitude":10972.800000000001,"velocity":196.517608,"heading":315,"on_ground":false}]},{"timestamp":1777168539,"aircraft":[{"icao24":"ae1235","callsign":"RCH694","country":"USA","lat":49.114995,"lon":14.961739,"altitude":9448.800000000001,"velocity":252.07756,"heading":102.48,"on_ground":false},{"icao24":"ae146f","callsign":"RCH652","country":"USA","lat":48.833252,"lon":16.778427,"altitude":8229.6,"velocity":267.51088,"heading":104,"on_ground":false},{"icao24":"ae0677","callsign":"MOOSE43","country":"USA","lat":48.883102,"lon":17.658229,"altitude":10965.18,"velocity":203.71982400000002,"heading":294,"on_ground":false}]},{"timestamp":1777168844,"aircraft":[{"icao24":"ae1235","callsign":"RCH694","country":"USA","lat":48.958526,"lon":15.989347,"altitude":9448.800000000001,"velocity":253.106448,"heading":103.36,"on_ground":false},{"icao24":"ae0677","callsign":"MOOSE43","country":"USA","lat":49.098702,"lon":16.911205,"altitude":10972.800000000001,"velocity":186.22872800000002,"heading":289,"on_ground":false},{"icao24":"ae146f","callsign":"RCH652","country":"USA","lat":48.492809,"lon":17.748135,"altitude":8229.6,"velocity":275.22754000000003,"heading":133,"on_ground":false},{"icao24":"ae119b","callsign":"RCH441","country":"USA","lat":48.18812,"lon":18.049201,"altitude":10972.800000000001,"velocity":202.176492,"heading":309,"on_ground":false}]},{"timestamp":1777169137,"aircraft":[{"icao24":"ae0677","callsign":"MOOSE43","country":"USA","lat":49.267741,"lon":16.19345,"altitude":10972.800000000001,"velocity":192.9165,"heading":290,"on_ground":false},{"icao24":"ae1235","callsign":"RCH694","country":"USA","lat":48.800016,"lon":16.975463,"altitude":9448.800000000001,"velocity":256.193112,"heading":104.06,"on_ground":false},{"icao24":"ae119b","callsign":"RCH441","country":"USA","lat":48.524705,"lon":17.414756,"altitude":10965.18,"velocity":208.864264,"heading":315,"on_ground":false},{"icao24":"ae146f","callsign":"RCH652","country":"USA","lat":48.012372,"lon":18.502056,"altitude":8229.6,"velocity":259.279776,"heading":133,"on_ground":false}]},{"timestamp":1777169439,"aircraft":[{"icao24":"ae144d","callsign":"RCH425","country":"USA","lat":49.838429,"lon":12.159756,"altitude":9448.800000000001,"velocity":240.759792,"heading":98,"on_ground":false},{"icao24":"ae0677","callsign":"MOOSE43","country":"USA","lat":49.442675,"lon":15.421101,"altitude":10965.18,"velocity":199.604272,"heading":289,"on_ground":false},{"icao24":"ae119b","callsign":"RCH441","country":"USA","lat":48.89281,"lon":16.785891,"altitude":10972.800000000001,"velocity":198.575384,"heading":291,"on_ground":false},{"icao24":"ae1235","callsign":"RCH694","country":"USA","lat":48.368954,"lon":17.795439,"altitude":9448.800000000001,"velocity":261.337552,"heading":131.84,"on_ground":false}]},{"timestamp":1777169739,"aircraft":[{"icao24":"ae144d","callsign":"RCH425","country":"USA","lat":49.67624,"lon":13.127749,"altitude":9448.800000000001,"velocity":242.817568,"heading":107,"on_ground":false},{"icao24":"ae0677","callsign":"MOOSE43","country":"USA","lat":49.612382,"lon":14.6421,"altitude":10972.800000000001,"velocity":190.858724,"heading":290,"on_ground":false},{"icao24":"ae119b","callsign":"RCH441","country":"USA","lat":49.128529,"lon":16.032163,"altitude":10972.800000000001,"velocity":207.320932,"heading":295,"on_ground":false}]},{"timestamp":1777170040,"aircraft":[{"icao24":"ae0677","callsign":"MOOSE43","country":"USA","lat":49.780839,"lon":13.838438,"altitude":10972.800000000001,"velocity":199.604272,"heading":288,"on_ground":false},{"icao24":"ae144d","callsign":"RCH425","country":"USA","lat":49.471856,"lon":14.099231,"altitude":9448.800000000001,"velocity":249.50534000000002,"heading":108,"on_ground":false},{"icao24":"ae119b","callsign":"RCH441","country":"USA","lat":49.365975,"lon":15.256519,"altitude":10972.800000000001,"velocity":210.407596,"heading":299,"on_ground":false}]},{"timestamp":1777170337,"aircraft":[{"icao24":"ae0677","callsign":"MOOSE43","country":"USA","lat":49.843724,"lon":13.010446,"altitude":10972.800000000001,"velocity":204.23426800000001,"heading":273,"on_ground":false},{"icao24":"ae119b","callsign":"RCH441","country":"USA","lat":49.593314,"lon":14.487468,"altitude":10972.800000000001,"velocity":214.523148,"heading":293,"on_ground":false},{"icao24":"ae144d","callsign":"RCH425","country":"USA","lat":49.261665,"lon":15.051099,"altitude":9448.800000000001,"velocity":254.64978,"heading":109,"on_ground":false}]},{"timestamp":1777170641,"aircraft":[{"icao24":"ae0677","callsign":"MOOSE43","country":"USA","lat":49.876977,"lon":12.14894,"altitude":10972.800000000001,"velocity":201.662048,"heading":275,"on_ground":false},{"icao24":"ae119b","callsign":"RCH441","country":"USA","lat":49.824551,"lon":13.678887,"altitude":10972.800000000001,"velocity":206.806488,"heading":293,"on_ground":false},{"icao24":"ae144d","callsign":"RCH425","country":"USA","lat":49.037439,"lon":16.018734,"altitude":9448.800000000001,"velocity":244.36090000000002,"heading":112,"on_ground":false}]},{"timestamp":1777170937,"aircraft":[{"icao24":"ae119b","callsign":"RCH441","country":"USA","lat":50.043163,"lon":12.887419,"altitude":10972.800000000001,"velocity":211.436484,"heading":293,"on_ground":false},{"icao24":"ae144d","callsign":"RCH425","country":"USA","lat":48.81007,"lon":16.967234,"altitude":9448.800000000001,"velocity":254.135336,"heading":111,"on_ground":false}]},{"timestamp":1777171239,"aircraft":[{"icao24":"ae119b","callsign":"RCH441","country":"USA","lat":50.181102,"lon":12.050635,"altitude":10408.92,"velocity":226.86980400000002,"heading":253,"on_ground":false},{"icao24":"ae144d","callsign":"RCH425","country":"USA","lat":48.360311,"lon":17.759694,"altitude":9448.800000000001,"velocity":262.36644,"heading":132,"on_ground":false}]},{"timestamp":1777171540,"aircraft":[]},{"timestamp":1777171840,"aircraft":[]},{"timestamp":1777172137,"aircraft":[{"icao24":"ae07fd","callsign":"RCH710","country":"USA","lat":48.794464,"lon":17.505962,"altitude":10363.2,"velocity":207.835376,"heading":288.81,"on_ground":false}]},{"timestamp":1777172449,"aircraft":[{"icao24":"ae07fd","callsign":"RCH710","country":"USA","lat":48.972809,"lon":16.666027,"altitude":10363.2,"velocity":210.92204,"heading":287.93,"on_ground":false}]},{"timestamp":1777172737,"aircraft":[{"icao24":"ae07fd","callsign":"RCH710","country":"USA","lat":49.13495,"lon":15.868138,"altitude":10363.2,"velocity":212.979816,"heading":287.23,"on_ground":false}]}]}