{"timestamp":1776328804,"count":4,"aircraft":[{"icao24":"480c43","callsign":"MMF22","country":"France","lat":52.148712,"lon":12.340698,"altitude":6096,"velocity":180.00395559999998,"heading":331.68,"on_ground":false},{"icao24":"ae20c8","callsign":"RCH135","country":"USA","lat":49.903543,"lon":13.810892,"altitude":10363.2,"velocity":209.89315200000001,"heading":287.23,"on_ground":false},{"icao24":"48d842","callsign":"PLF048","country":"Poland","lat":51.395939,"lon":17.823316,"altitude":4572,"velocity":140.95765600000001,"heading":69,"on_ground":false},{"icao24":"477ff5","callsign":"HUF179","country":"Hungary","lat":48.28418,"lon":20.432528,"altitude":8526.78,"velocity":219.8733656,"heading":19.83,"on_ground":false}]}