{"timestamp":1777043914,"count":10,"aircraft":[{"icao24":"ae07e3","callsign":"RCH132","country":"USA","lat":49.810986,"lon":12.279127,"altitude":8229.6,"velocity":251.563116,"heading":87.0,"on_ground":false},{"icao24":"ae1471","callsign":"RCH149","country":"USA","lat":49.997309,"lon":13.234548,"altitude":10972.800000000001,"velocity":226.86980400000002,"heading":287.0,"on_ground":false},{"icao24":"4984b5","callsign":"CEF05C","country":"Czech Republic","lat":51.020927,"lon":15.383682,"altitude":5494.02,"velocity":124.39255920000001,"heading":232.56,"on_ground":false},{"icao24":"ae07e4","callsign":"RCH436","country":"USA","lat":49.415452,"lon":15.707529,"altitude":10363.2,"velocity":203.20538,"heading":293.0,"on_ground":false},{"icao24":"ae20c7","callsign":"RCH593","country":"USA","lat":49.037895,"lon":17.167656,"altitude":10370.82,"velocity":219.667588,"heading":281.3,"on_ground":false},{"icao24":"ae6ca7","callsign":"HUNT41","country":"USA","lat":52.657145,"lon":17.48427,"altitude":457.20000000000005,"velocity":53.450731600000005,"heading":308.75,"on_ground":false},{"icao24":"48d842","callsign":"PLF033","country":"Poland","lat":48.920619,"lon":19.459794,"altitude":5486.400000000001,"velocity":112.148792,"heading":15.0,"on_ground":false},{"icao24":"48d82f","callsign":"PLF112","country":"Poland","lat":52.020454,"lon":20.99958,"altitude":1805.94,"velocity":92.59992,"heading":146.25,"on_ground":false},{"icao24":"48d982","callsign":"PLF102","country":"Poland","lat":48.336914,"lon":21.430594,"altitude":10972.800000000001,"velocity":202.690936,"heading":344.69,"on_ground":false},{"icao24":"48d960","callsign":"PLF105","country":"Poland","lat":52.409958,"lon":21.788788,"altitude":3848.1000000000004,"velocity":166.679856,"heading":211.24,"on_ground":false}]}