{"timestamp":1778053829,"count":8,"aircraft":[{"icao24":"3f660d","callsign":"EDGE61","country":"Germany","lat":54.044557,"lon":12.682673,"altitude":2735.58,"velocity":null,"heading":null,"on_ground":false},{"icao24":"3f4f9c","callsign":"SHADO13","country":"Germany","lat":51.856824,"lon":13.501977,"altitude":1600.2,"velocity":63.276612,"heading":347,"on_ground":false},{"icao24":"480886","callsign":"NAF301A","country":"Netherlands","lat":55.783221,"lon":13.549833,"altitude":365.76,"velocity":70.94182760000001,"heading":240.46,"on_ground":false},{"icao24":"ae0582","callsign":"RCH2061","country":"USA","lat":49.693723,"lon":14.557484,"altitude":11582.400000000001,"velocity":215.03759200000002,"heading":290.04,"on_ground":false},{"icao24":"3e8764","callsign":"GAF313","country":"Germany","lat":55.90677,"lon":17.314711,"altitude":6705.6,"velocity":140.2374344,"heading":233.8,"on_ground":false},{"icao24":"ae0813","callsign":"RCH572","country":"USA","lat":48.620554,"lon":17.529698,"altitude":8229.6,"velocity":249.55678440000003,"heading":124.25,"on_ground":false},{"icao24":"ae080b","callsign":"MOOSE52","country":"USA","lat":48.503165,"lon":17.713297,"altitude":10210.800000000001,"velocity":242.817568,"heading":135,"on_ground":false},{"icao24":"48da43","callsign":"PLF633","country":"Poland","lat":52.887222,"lon":21.735153,"altitude":556.26,"velocity":61.218836,"heading":45.2,"on_ground":false}]}