{"timestamp":1776691235,"count":8,"aircraft":[{"icao24":"3f9a2c","callsign":"GAFS73A","country":"Germany","lat":53.661718,"lon":16.572896,"altitude":9456.42,"velocity":253.620892,"heading":94,"on_ground":false},{"icao24":"3e865f","callsign":"GAF011","country":"Germany","lat":53.037846,"lon":17.099399,"altitude":7010.400000000001,"velocity":165.136524,"heading":80,"on_ground":false},{"icao24":"ae59d3","callsign":"EASY20","country":"USA","lat":52.301468,"lon":17.795868,"altitude":null,"velocity":63.791056000000005,"heading":38.4,"on_ground":true},{"icao24":"ae07ec","callsign":"RCH3248","country":"USA","lat":48.336632,"lon":18.852467,"altitude":10972.800000000001,"velocity":204.23426800000001,"heading":306,"on_ground":false},{"icao24":"48d8f1","callsign":"HACHT02","country":"Poland","lat":52.566101,"lon":19.137039,"altitude":3566.1600000000003,"velocity":127.067668,"heading":234.06,"on_ground":false},{"icao24":"adfe5f","callsign":"HACHT03","country":"USA","lat":52.594528,"lon":19.259338,"altitude":2926.08,"velocity":141.7807664,"heading":253.34,"on_ground":false},{"icao24":"48d82d","callsign":"PLF116","country":"Poland","lat":50.120278,"lon":19.763469,"altitude":1356.3600000000001,"velocity":55.559952,"heading":353.85,"on_ground":false},{"icao24":"adfebb","callsign":"DUKE60","country":"USA","lat":50.25824,"lon":21.983209,"altitude":2125.98,"velocity":123.0035604,"heading":107.53,"on_ground":false}]}