{"timestamp":1777371030,"count":3,"aircraft":[{"icao24":"ae07ef","callsign":"MOOSE93","country":"USA","lat":49.44744,"lon":15.58123,"altitude":10363.2,"velocity":216.580924,"heading":292,"on_ground":false},{"icao24":"ae6cbd","callsign":"HUNT49","country":"USA","lat":53.168894,"lon":16.184073,"altitude":335.28000000000003,"velocity":64.048278,"heading":128.8,"on_ground":false},{"icao24":"480c45","callsign":"MMF18","country":"France","lat":51.327929,"lon":19.269683,"altitude":7924.8,"velocity":145.073208,"heading":285.29,"on_ground":false}]}