{"timestamp":1776858016,"count":10,"aircraft":[{"icao24":"3f7dc1","callsign":"GAF830","country":"Germany","lat":52.376714,"lon":12.340393,"altitude":6225.54,"velocity":218.6387,"heading":281.12,"on_ground":false},{"icao24":"ae144b","callsign":"RCH219","country":"USA","lat":50.041544,"lon":12.532114,"altitude":10363.2,"velocity":243.84645600000002,"heading":287,"on_ground":false},{"icao24":"480440","callsign":"NAF298A","country":"Netherlands","lat":51.743418,"lon":12.985153,"altitude":22.86,"velocity":57.2576172,"heading":85.88,"on_ground":false},{"icao24":"3ebb80","callsign":"GAF662","country":"Germany","lat":52.328595,"lon":13.558789,"altitude":220.98000000000002,"velocity":59.16106,"heading":10,"on_ground":false},{"icao24":"3f496e","callsign":"GAF664","country":"Germany","lat":52.330948,"lon":13.55896,"altitude":228.60000000000002,"velocity":52.987732,"heading":358.89,"on_ground":false},{"icao24":"4d03c3","callsign":"NATO01","country":"NATO","lat":49.034962,"lon":14.58276,"altitude":9448.800000000001,"velocity":180.51839959999998,"heading":40.96,"on_ground":false},{"icao24":"48d82f","callsign":"PLF118","country":"Poland","lat":51.855948,"lon":19.486331,"altitude":3040.38,"velocity":70.993272,"heading":298.3,"on_ground":false},{"icao24":"48d856","callsign":"PLF042A","country":"Poland","lat":50.16819,"lon":19.893871,"altitude":548.64,"velocity":95.686584,"heading":33.4,"on_ground":false},{"icao24":"48d982","callsign":"PLF120","country":"Poland","lat":51.134992,"lon":20.366702,"altitude":8534.4,"velocity":216.06648,"heading":335.21,"on_ground":false},{"icao24":"48da43","callsign":"PLF633","country":"Poland","lat":52.161255,"lon":20.932541,"altitude":182.88,"velocity":46.814404,"heading":236.66,"on_ground":false}]}