{"timestamp":1773584993,"count":4,"aircraft":[{"icao24":"4a91f8","callsign":"SAS1678","country":"Sweden","lat":54.5539,"lon":12.7987,"altitude":6301.74,"velocity":166.99,"heading":352.74,"on_ground":false},{"icao24":"4a9d65","callsign":"SEGKE","country":"Sweden","lat":55.569,"lon":13.369,"altitude":220.98,"velocity":43.73,"heading":171.2,"on_ground":false},{"icao24":"48d8f1","callsign":"PLF252","country":"Poland","lat":52.3463,"lon":18.0247,"altitude":701.04,"velocity":71.42,"heading":288.04,"on_ground":false},{"icao24":"4b8e46","callsign":"PGT3DX","country":"Turkey","lat":48.5723,"lon":14.2452,"altitude":11582.4,"velocity":226.51,"heading":298.49,"on_ground":false}]}