{"timestamp":1776961817,"count":6,"aircraft":[{"icao24":"ae04f2","callsign":"DUKE22","country":"USA","lat":48.904129,"lon":12.147991,"altitude":6141.72,"velocity":146.56509559999998,"heading":297.37,"on_ground":false},{"icao24":"480c41","callsign":"MMF37","country":"France","lat":51.157604,"lon":12.49794,"altitude":3657.6000000000004,"velocity":196.6204968,"heading":268.05,"on_ground":false},{"icao24":"48d82f","callsign":"PLF118","country":"Poland","lat":52.010555,"lon":17.738588,"altitude":3040.38,"velocity":66.87772,"heading":15.12,"on_ground":false},{"icao24":"ae29dd","callsign":null,"country":"USA","lat":48.434624,"lon":18.215622,"altitude":8221.98,"velocity":158.963196,"heading":121,"on_ground":false},{"icao24":"3b77f8","callsign":"CTM3922","country":"France","lat":53.369813,"lon":18.511559,"altitude":7620,"velocity":134.527106,"heading":68.93,"on_ground":false},{"icao24":"48d852","callsign":"PLF044B","country":"Poland","lat":49.886605,"lon":20.048519,"altitude":609.6,"velocity":96.715472,"heading":122,"on_ground":false}]}