{"timestamp":1774083935,"count":3,"aircraft":[{"icao24":"3e854f","callsign":"GAF920","country":"Germany","lat":52.373028,"lon":13.493347,"altitude":null,"velocity":12.603878,"heading":null,"on_ground":true},{"icao24":"3b75ec","callsign":"CTM2077","country":"France","lat":51.322449,"lon":14.466248,"altitude":5791.200000000001,"velocity":146.9766508,"heading":94.01,"on_ground":false},{"icao24":"ae1242","callsign":"RCH574","country":"USA","lat":49.601565,"lon":14.692407,"altitude":10363.2,"velocity":225.326472,"heading":288,"on_ground":false}]}