{"timestamp":1775732434,"count":10,"aircraft":[{"icao24":"ae0803","callsign":"RCH3267","country":"USA","lat":49.830584,"lon":12.18727,"altitude":8229.6,"velocity":234.586464,"heading":95,"on_ground":false},{"icao24":"ae138a","callsign":"RCH647","country":"USA","lat":49.650209,"lon":13.249034,"altitude":7627.620000000001,"velocity":167.1943,"heading":108,"on_ground":false},{"icao24":"ae2208","callsign":null,"country":"USA","lat":49.552137,"lon":13.849943,"altitude":7924.8,"velocity":184.685396,"heading":106,"on_ground":false},{"icao24":"ae080e","callsign":"RCH4530","country":"USA","lat":49.443762,"lon":15.733959,"altitude":9144,"velocity":205.7776,"heading":294,"on_ground":false},{"icao24":"ae144f","callsign":"RCH1892","country":"USA","lat":49.331363,"lon":15.972442,"altitude":10972.800000000001,"velocity":205.7776,"heading":290,"on_ground":false},{"icao24":"3f46db","callsign":"GAF127","country":"Germany","lat":51.648468,"lon":16.472737,"altitude":8801.1,"velocity":189.315392,"heading":291.69,"on_ground":false},{"icao24":"48d855","callsign":"PLF040","country":"Poland","lat":50.099246,"lon":19.945415,"altitude":769.62,"velocity":88.484368,"heading":257.87,"on_ground":false},{"icao24":"48d982","callsign":"PLF120","country":"Poland","lat":51.949365,"lon":21.155273,"altitude":861.0600000000001,"velocity":92.0340316,"heading":332.72,"on_ground":false},{"icao24":"ae04f2","callsign":"DUKE29","country":"USA","lat":50.109512,"lon":22.050356,"altitude":190.5,"velocity":50.929956000000004,"heading":271.8,"on_ground":false},{"icao24":"3f7dc1","callsign":"GAF817","country":"Germany","lat":54.931229,"lon":24.25959,"altitude":2255.52,"velocity":143.73565359999998,"heading":284.93,"on_ground":false}]}