{"timestamp":1772716558,"count":3,"aircraft":[{"icao24":"ae6cc0","callsign":"HUNT21","country":"USA","lat":52.3791,"lon":17.8646,"altitude":60.96,"velocity":0.51,"heading":270.0,"on_ground":false},{"icao24":"498489","callsign":"CEF630","country":"Czech Republic","lat":51.582,"lon":22.0585,"altitude":1424.94,"velocity":127.82,"heading":119.14,"on_ground":false},{"icao24":"3f5342","callsign":"GAF196","country":"Germany","lat":51.4096,"lon":12.1645,"altitude":228.6,"velocity":68.0,"heading":86.96,"on_ground":false}]}