{"timestamp":1776262507,"count":3,"aircraft":[{"icao24":"48d823","callsign":"@@@@@@@@","country":"Poland","lat":51.429024,"lon":17.155514,"altitude":3322.32,"velocity":95.686584,"heading":155,"on_ground":false},{"icao24":"ae1199","callsign":"RCH1834","country":"USA","lat":48.931761,"lon":17.508746,"altitude":10972.800000000001,"velocity":218.6387,"heading":297,"on_ground":false},{"icao24":"ae6cc0","callsign":"HUNT29","country":"USA","lat":52.381165,"lon":17.824631,"altitude":null,"velocity":0.514444,"heading":148.6,"on_ground":true}]}