{"timestamp":1775916323,"count":4,"aircraft":[{"icao24":"4a8199","callsign":"SVF624","country":"Sweden","lat":55.688644,"lon":13.707775,"altitude":4122.42,"velocity":184.5310628,"heading":43.08,"on_ground":false},{"icao24":"ae123e","callsign":"RCH633","country":"USA","lat":49.564316,"lon":14.86602,"altitude":10972.800000000001,"velocity":195.23149800000002,"heading":288.43,"on_ground":false},{"icao24":"33ffb7","callsign":"IAM4661","country":"Italy","lat":49.288087,"lon":16.538351,"altitude":7322.820000000001,"velocity":137.356548,"heading":230,"on_ground":false},{"icao24":"ae293b","callsign":"HKY764","country":"USA","lat":48.352145,"lon":17.930395,"altitude":8534.4,"velocity":141.986544,"heading":315,"on_ground":false}]}