{"timestamp":1774713024,"count":5,"aircraft":[{"icao24":"ae1237","callsign":"RCH818","country":"USA","lat":50.012137,"lon":12.008858,"altitude":10972.800000000001,"velocity":211.436484,"heading":255,"on_ground":false},{"icao24":"ae123b","callsign":"RCH702","country":"USA","lat":49.714472,"lon":14.086452,"altitude":10363.2,"velocity":243.332012,"heading":286,"on_ground":false},{"icao24":"ae5c9d","callsign":"HKY745","country":"USA","lat":49.76665,"lon":14.213418,"altitude":7924.8,"velocity":180.56984400000002,"heading":295,"on_ground":false},{"icao24":"ae080f","callsign":"RCH455","country":"USA","lat":48.152332,"lon":18.628945,"altitude":10980.42,"velocity":256.193112,"heading":317,"on_ground":false},{"icao24":"ae035d","callsign":null,"country":"USA","lat":48.122256,"lon":19.301188,"altitude":12192,"velocity":250.01978400000002,"heading":306.04,"on_ground":false}]}