{"timestamp":1776925226,"count":5,"aircraft":[{"icao24":"ae03f9","callsign":"DUKE60","country":"USA","lat":48.263672,"lon":14.178561,"altitude":8229.6,"velocity":125.67866920000002,"heading":104.95,"on_ground":false},{"icao24":"ae49c6","callsign":"RCH233","country":"USA","lat":49.318004,"lon":14.800915,"altitude":8839.2,"velocity":217.609812,"heading":109,"on_ground":false},{"icao24":"ae145c","callsign":"RCH278","country":"USA","lat":49.169608,"lon":15.466988,"altitude":8298.18,"velocity":226.86980400000002,"heading":106,"on_ground":false},{"icao24":"ae144d","callsign":"RCH137","country":"USA","lat":48.525429,"lon":17.679352,"altitude":8831.58,"velocity":215.55203600000002,"heading":135,"on_ground":false},{"icao24":"4984b5","callsign":"CEF05C","country":"Czech Republic","lat":51.857574,"lon":19.789272,"altitude":5181.6,"velocity":113.4863464,"heading":59.48,"on_ground":false}]}