{"timestamp":1776252642,"count":5,"aircraft":[{"icao24":"33fca2","callsign":"IAM3140","country":"Italy","lat":49.707688,"lon":12.829062,"altitude":10972.800000000001,"velocity":224.5033616,"heading":8.17,"on_ground":false},{"icao24":"48d846","callsign":"PLF040","country":"Poland","lat":52.351178,"lon":15.194189,"altitude":5486.400000000001,"velocity":null,"heading":null,"on_ground":false},{"icao24":"468111","callsign":"HAF352C","country":"Greece","lat":49.640854,"lon":16.16378,"altitude":13106.400000000001,"velocity":244.6695664,"heading":324.67,"on_ground":false},{"icao24":"ae59d2","callsign":"EASY22","country":"USA","lat":51.969452,"lon":16.479721,"altitude":373.38,"velocity":65.848832,"heading":72.5,"on_ground":false},{"icao24":"4984b5","callsign":"CEF647","country":"Czech Republic","lat":52.437698,"lon":21.320114,"altitude":4876.8,"velocity":125.1127808,"heading":209.83,"on_ground":false}]}