{"timestamp":1776239144,"count":6,"aircraft":[{"icao24":"3f447a","callsign":"PRIMR21","country":"Germany","lat":54.066147,"lon":12.003427,"altitude":6088.38,"velocity":161.9469712,"heading":316.67,"on_ground":false},{"icao24":"48d82f","callsign":"PLF111","country":"Poland","lat":48.907509,"lon":12.239998,"altitude":3360.42,"velocity":77.1666,"heading":24.61,"on_ground":false},{"icao24":"3f4406","callsign":"SHADO12","country":"Germany","lat":51.857407,"lon":12.899384,"altitude":1120.14,"velocity":64.819944,"heading":281,"on_ground":false},{"icao24":"33fe92","callsign":"IAM1419","country":"Italy","lat":48.803375,"lon":14.216449,"altitude":10073.640000000001,"velocity":225.326472,"heading":23.4,"on_ground":false},{"icao24":"ae2fa3","callsign":"RCH316","country":"USA","lat":49.402567,"lon":14.421167,"altitude":8229.6,"velocity":233.557576,"heading":107,"on_ground":false},{"icao24":"4984b5","callsign":"CEF647","country":"Czech Republic","lat":51.463452,"lon":18.121719,"altitude":4579.62,"velocity":133.1381072,"heading":69.88,"on_ground":false}]}