{"timestamp":1776342902,"count":8,"aircraft":[{"icao24":"3f76f4","callsign":"GAF951","country":"Germany","lat":52.412765,"lon":13.061455,"altitude":190.5,"velocity":44.756628,"heading":24,"on_ground":false},{"icao24":"3ebd41","callsign":"GAF623","country":"Germany","lat":51.215012,"lon":13.779379,"altitude":853.44,"velocity":105.3581312,"heading":59.8,"on_ground":false},{"icao24":"ae2fac","callsign":"RCH1848","country":"USA","lat":49.605499,"lon":14.7765,"altitude":12192,"velocity":209.37870800000002,"heading":288,"on_ground":false},{"icao24":"ae6cb5","callsign":"HUNT24","country":"USA","lat":51.715618,"lon":15.37292,"altitude":731.52,"velocity":70.47882800000001,"heading":70.6,"on_ground":false},{"icao24":"ae07f3","callsign":"RCH1838","country":"USA","lat":48.609055,"lon":17.554924,"altitude":9441.18,"velocity":257.736444,"heading":136.8,"on_ground":false},{"icao24":"ae0669","callsign":null,"country":"USA","lat":50.886497,"lon":18.971754,"altitude":7620,"velocity":223.268696,"heading":78.57,"on_ground":false},{"icao24":"3b7564","callsign":"TTAL91","country":"France","lat":53.018738,"lon":19.060974,"altitude":11376.66,"velocity":218.94736640000002,"heading":251.65,"on_ground":false},{"icao24":"44f685","callsign":"BAF651","country":"Belgium","lat":51.195969,"lon":19.660702,"altitude":9745.980000000001,"velocity":179.798178,"heading":308.38,"on_ground":false}]}