{"timestamp":1774277719,"count":6,"aircraft":[{"icao24":"3f45e5","callsign":"EDGE01T","country":"Germany","lat":49.107196,"lon":12.063245,"altitude":3108.96,"velocity":168.737632,"heading":5,"on_ground":false},{"icao24":"ae1f78","callsign":"R72105","country":"USA","lat":48.31424,"lon":12.17979,"altitude":883.9200000000001,"velocity":56.8975064,"heading":12.53,"on_ground":false},{"icao24":"ae08f0","callsign":"RUBIK33","country":"USA","lat":49.189133,"lon":16.05342,"altitude":8534.4,"velocity":144.1472088,"heading":294,"on_ground":false},{"icao24":"ae6cb2","callsign":"HUNT21","country":"USA","lat":52.36098,"lon":17.876561,"altitude":274.32,"velocity":51.4444,"heading":null,"on_ground":false},{"icao24":"3f59f3","callsign":"GAF722","country":"Germany","lat":48.240687,"lon":20.597052,"altitude":11582.400000000001,"velocity":239.0106824,"heading":303.14,"on_ground":false},{"icao24":"48d981","callsign":"PLF130","country":"Poland","lat":50.436127,"lon":21.066935,"altitude":7315.200000000001,"velocity":186.38306120000001,"heading":292.39,"on_ground":false}]}