{"timestamp":1775137226,"count":3,"aircraft":[{"icao24":"ae146c","callsign":"MOOSE85","country":"USA","lat":49.539598,"lon":13.84614,"altitude":9448.800000000001,"velocity":246.93312,"heading":100,"on_ground":false},{"icao24":"ae6cb2","callsign":"HUNT29","country":"USA","lat":52.357954,"lon":17.633684,"altitude":914.4000000000001,"velocity":46.197071199999996,"heading":286.82,"on_ground":false},{"icao24":"33ffbf","callsign":"IAM4669","country":"Italy","lat":52.384249,"lon":21.654311,"altitude":7307.58,"velocity":155.876532,"heading":33,"on_ground":false}]}