{"timestamp":1776803722,"count":6,"aircraft":[{"icao24":"3f48df","callsign":"GAF951","country":"Germany","lat":52.373078,"lon":13.435879,"altitude":243.84,"velocity":38.068856000000004,"heading":136,"on_ground":false},{"icao24":"ae4bdc","callsign":"RCH700","country":"USA","lat":49.207844,"lon":15.289381,"altitude":8229.6,"velocity":159.47764,"heading":108,"on_ground":false},{"icao24":"ae6cc0","callsign":"HUNT21","country":"USA","lat":52.395195,"lon":17.823826,"altitude":60.96,"velocity":12.346656,"heading":126.1,"on_ground":false},{"icao24":"ae144d","callsign":"RCH137","country":"USA","lat":48.133339,"lon":19.279667,"altitude":10972.800000000001,"velocity":221.21092000000002,"heading":314.5,"on_ground":false},{"icao24":"48d82d","callsign":"PLF118B","country":"Poland","lat":50.025646,"lon":19.698656,"altitude":1173.48,"velocity":89.513256,"heading":167.34,"on_ground":false},{"icao24":"48da43","callsign":"PLF633","country":"Poland","lat":52.15736,"lon":20.692435,"altitude":274.32,"velocity":60.3442812,"heading":119.62,"on_ground":false}]}