{"timestamp":1776868516,"count":4,"aircraft":[{"icao24":"3f75d6","callsign":"LK01","country":"Germany","lat":48.706454,"lon":12.293218,"altitude":1036.3200000000002,"velocity":153.818756,"heading":237,"on_ground":false},{"icao24":"3e95ca","callsign":"GAF621","country":"Germany","lat":52.37653,"lon":13.502388,"altitude":null,"velocity":14.147210000000001,"heading":54.7,"on_ground":true},{"icao24":"adfe81","callsign":"HKY797","country":"USA","lat":49.791901,"lon":14.200423,"altitude":7924.8,"velocity":168.223188,"heading":289.1,"on_ground":false},{"icao24":"48d82d","callsign":"PLF115","country":"Poland","lat":54.209275,"lon":16.974369,"altitude":3055.6200000000003,"velocity":93.628808,"heading":121.99,"on_ground":false}]}