{"timestamp":1776365402,"count":6,"aircraft":[{"icao24":"ae1468","callsign":"RCH153","country":"USA","lat":49.799061,"lon":12.019366,"altitude":8229.6,"velocity":255.16422400000002,"heading":89,"on_ground":false},{"icao24":"ae146c","callsign":"MOOSE73","country":"USA","lat":50.151116,"lon":12.523081,"altitude":10363.2,"velocity":200.63316,"heading":288.11,"on_ground":false},{"icao24":"ae07fa","callsign":"RCH1824","country":"USA","lat":49.831177,"lon":13.498556,"altitude":11582.400000000001,"velocity":214.008704,"heading":260,"on_ground":false},{"icao24":"480c43","callsign":"MMF11","country":"France","lat":50.073449,"lon":15.555304,"altitude":6400.8,"velocity":178.9236232,"heading":280.44,"on_ground":false},{"icao24":"ae07ea","callsign":"MOOSE70","country":"USA","lat":48.764329,"lon":17.7685,"altitude":11582.400000000001,"velocity":211.950928,"heading":295,"on_ground":false},{"icao24":"48da43","callsign":"PLF633","country":"Poland","lat":51.997101,"lon":19.152298,"altitude":853.44,"velocity":64.9742772,"heading":94.09,"on_ground":false}]}