{"timestamp":1774659035,"count":3,"aircraft":[{"icao24":"ae49c2","callsign":"MOOSE54","country":"USA","lat":49.781916,"lon":12.604266,"altitude":9448.800000000001,"velocity":232.01424400000002,"heading":109,"on_ground":false},{"icao24":"ae07ec","callsign":"MOOSE96","country":"USA","lat":48.89726,"lon":17.612746,"altitude":10363.2,"velocity":240.8626808,"heading":296.78,"on_ground":false},{"icao24":"ae1465","callsign":"MOOSE68","country":"USA","lat":48.321057,"lon":18.885513,"altitude":11582.400000000001,"velocity":251.563116,"heading":305,"on_ground":false}]}