{"timestamp":1774878606,"count":6,"aircraft":[{"icao24":"ae2faa","callsign":"RCH571","country":"USA","lat":49.988744,"lon":13.268457,"altitude":11582.400000000001,"velocity":231.4998,"heading":288,"on_ground":false},{"icao24":"48d980","callsign":"PLF110","country":"Poland","lat":55.789215,"lon":13.319841,"altitude":10668,"velocity":241.78868,"heading":130.95,"on_ground":false},{"icao24":"ae20c7","callsign":"RCH590","country":"USA","lat":49.178254,"lon":15.395026,"altitude":8298.18,"velocity":228.413136,"heading":110,"on_ground":false},{"icao24":"ae6cb2","callsign":null,"country":"USA","lat":52.397337,"lon":17.780901,"altitude":701.0400000000001,"velocity":53.759398000000004,"heading":291.9,"on_ground":false},{"icao24":"ae1465","callsign":"MOOSE72","country":"USA","lat":48.056865,"lon":19.420471,"altitude":10972.800000000001,"velocity":210.92204,"heading":312,"on_ground":false},{"icao24":"48d822","callsign":"@@@@@@@@","country":"Poland","lat":51.826826,"lon":20.115861,"altitude":3048,"velocity":83.339928,"heading":293,"on_ground":false}]}