{"timestamp":1775384430,"count":3,"aircraft":[{"icao24":"ae144f","callsign":"MOOSE34","country":"USA","lat":49.629492,"lon":13.35932,"altitude":9448.800000000001,"velocity":253.106448,"heading":107,"on_ground":false},{"icao24":"ae123b","callsign":"RCH1863","country":"USA","lat":49.265249,"lon":15.036499,"altitude":8229.6,"velocity":251.048672,"heading":110,"on_ground":false},{"icao24":"ae055f","callsign":"RCH2046","country":"USA","lat":52.306926,"lon":15.254468,"altitude":8747.76,"velocity":261.337552,"heading":100.02,"on_ground":false}]}