{"timestamp":1775746533,"count":5,"aircraft":[{"icao24":"ae0a54","callsign":"DUKE60","country":"USA","lat":51.546432,"lon":14.500023,"altitude":8534.4,"velocity":144.9703192,"heading":252.66,"on_ground":false},{"icao24":"ae056a","callsign":"RCH2032","country":"USA","lat":48.7112,"lon":17.202601,"altitude":9448.800000000001,"velocity":266.481992,"heading":131.84,"on_ground":false},{"icao24":"ae2208","callsign":null,"country":"USA","lat":49.023724,"lon":17.204409,"altitude":7620,"velocity":158.448752,"heading":287,"on_ground":false},{"icao24":"ae6cbd","callsign":"HUNT44","country":"USA","lat":51.991196,"lon":17.971344,"altitude":243.84,"velocity":53.2963984,"heading":130.3,"on_ground":false},{"icao24":"48d960","callsign":"PLF105","country":"Poland","lat":51.873857,"lon":21.301346,"altitude":1516.38,"velocity":115.7499,"heading":297.82,"on_ground":false}]}