{"timestamp":1776627038,"count":5,"aircraft":[{"icao24":"ae1242","callsign":"RCH416","country":"USA","lat":49.805786,"lon":12.478666,"altitude":9448.800000000001,"velocity":242.303124,"heading":96,"on_ground":false},{"icao24":"ae1468","callsign":"RCH1806","country":"USA","lat":49.668578,"lon":14.349359,"altitude":9144,"velocity":205.7776,"heading":296,"on_ground":false},{"icao24":"ae145d","callsign":"RCH176","country":"USA","lat":49.379345,"lon":15.708624,"altitude":9144,"velocity":231.4998,"heading":285,"on_ground":false},{"icao24":"ae123f","callsign":"RCH4593","country":"USA","lat":48.725894,"lon":17.789202,"altitude":9608.82,"velocity":221.725364,"heading":309,"on_ground":false},{"icao24":"ae1459","callsign":"RCH454","country":"USA","lat":48.13268,"lon":18.479418,"altitude":9448.800000000001,"velocity":242.817568,"heading":135.35,"on_ground":false}]}