{"timestamp":1777359027,"count":3,"aircraft":[{"icao24":"ae0677","callsign":"MOOSE95","country":"USA","lat":49.750527,"lon":13.985079,"altitude":10363.2,"velocity":206.806488,"heading":287.23,"on_ground":false},{"icao24":"477ff4","callsign":"HUF194","country":"Hungary","lat":48.477219,"lon":18.293754,"altitude":11582.400000000001,"velocity":197.8551624,"heading":295.9,"on_ground":false},{"icao24":"48d843","callsign":"PLF032","country":"Poland","lat":51.941989,"lon":20.446757,"altitude":3931.92,"velocity":107.51879600000001,"heading":214,"on_ground":false}]}