{"timestamp":1776952821,"count":7,"aircraft":[{"icao24":"3f6398","callsign":"BONES1","country":"Germany","lat":53.97954,"lon":12.422685,"altitude":3154.6800000000003,"velocity":null,"heading":null,"on_ground":false},{"icao24":"ae03f9","callsign":"DUKE60","country":"USA","lat":52.256516,"lon":16.285113,"altitude":4282.4400000000005,"velocity":101.4483568,"heading":235.75,"on_ground":false},{"icao24":"33ffbf","callsign":"IAM4664","country":"Italy","lat":48.700315,"lon":16.720733,"altitude":7322.820000000001,"velocity":165.650968,"heading":243,"on_ground":false},{"icao24":"ae048a","callsign":null,"country":"USA","lat":48.96579,"lon":17.506996,"altitude":10347.960000000001,"velocity":214.9347032,"heading":307.61,"on_ground":false},{"icao24":"ae6cb8","callsign":"HUNT41","country":"USA","lat":52.335098,"lon":17.696384,"altitude":335.28000000000003,"velocity":62.247724,"heading":99.9,"on_ground":false},{"icao24":"ae1463","callsign":"MOOSE99","country":"USA","lat":48.617523,"lon":18.06265,"altitude":10363.2,"velocity":225.2750276,"heading":316.76,"on_ground":false},{"icao24":"48d855","callsign":"PLF038","country":"Poland","lat":49.079518,"lon":21.175416,"altitude":5486.400000000001,"velocity":104.94657600000001,"heading":337.32,"on_ground":false}]}