{"timestamp":1774659335,"count":3,"aircraft":[{"icao24":"ae49c2","callsign":"MOOSE54","country":"USA","lat":49.597955,"lon":13.505041,"altitude":9448.800000000001,"velocity":220.69647600000002,"heading":107,"on_ground":false},{"icao24":"ae07ec","callsign":"MOOSE96","country":"USA","lat":49.156556,"lon":16.722998,"altitude":10363.2,"velocity":235.100908,"heading":291.57,"on_ground":false},{"icao24":"ae1465","callsign":"MOOSE68","country":"USA","lat":48.709346,"lon":18.052816,"altitude":11582.400000000001,"velocity":251.048672,"heading":305,"on_ground":false}]}