{"timestamp":1776774004,"count":10,"aircraft":[{"icao24":"3f56e3","callsign":"LION01","country":"Germany","lat":54.288712,"lon":12.682019,"altitude":190.5,"velocity":79.89315320000001,"heading":252.38,"on_ground":false},{"icao24":"3f9a2c","callsign":"GAFS73A","country":"Germany","lat":53.832924,"lon":13.149715,"altitude":9456.42,"velocity":223.268696,"heading":97,"on_ground":false},{"icao24":"ae4e11","callsign":"LION490","country":"USA","lat":49.662271,"lon":13.191368,"altitude":8229.6,"velocity":169.25207600000002,"heading":107,"on_ground":false},{"icao24":"3f447a","callsign":"GAF011","country":"Germany","lat":52.7786,"lon":16.369001,"altitude":6873.240000000001,"velocity":136.53343759999998,"heading":95.84,"on_ground":false},{"icao24":"ae51e4","callsign":"CROSS23","country":"USA","lat":52.026718,"lon":16.747894,"altitude":685.8000000000001,"velocity":61.218836,"heading":72.5,"on_ground":false},{"icao24":"ae1449","callsign":"RCH455","country":"USA","lat":48.388381,"lon":17.885211,"altitude":8839.2,"velocity":237.67312800000002,"heading":135.35,"on_ground":false},{"icao24":"477ff5","callsign":"HUF183","country":"Hungary","lat":48.885315,"lon":18.777748,"altitude":10683.24,"velocity":234.586464,"heading":190.74,"on_ground":false},{"icao24":"3f97fd","callsign":"GAF894","country":"Germany","lat":50.474869,"lon":19.003378,"altitude":472.44,"velocity":69.2441624,"heading":81.03,"on_ground":false},{"icao24":"48d820","callsign":"PLF243","country":"Poland","lat":50.122012,"lon":19.477627,"altitude":1463.04,"velocity":76.13771200000001,"heading":264,"on_ground":false},{"icao24":"48d8f1","callsign":"FENIX70","country":"Poland","lat":49.973236,"lon":19.979144,"altitude":2407.92,"velocity":104.6379096,"heading":259.52,"on_ground":false}]}