{"timestamp":1776065128,"count":6,"aircraft":[{"icao24":"498486","callsign":"CEF643","country":"Czech Republic","lat":53.155334,"lon":13.983791,"altitude":5189.22,"velocity":119.6596744,"heading":184.19,"on_ground":false},{"icao24":"4984b5","callsign":"CEF648","country":"Czech Republic","lat":49.139557,"lon":15.254587,"altitude":6400.8,"velocity":103.660466,"heading":160.58,"on_ground":false},{"icao24":"ae4f12","callsign":"RCH136","country":"USA","lat":48.964111,"lon":17.573146,"altitude":10363.2,"velocity":226.35536000000002,"heading":310.08,"on_ground":false},{"icao24":"48d842","callsign":"PLF038","country":"Poland","lat":53.1335,"lon":19.425673,"altitude":5486.400000000001,"velocity":116.778788,"heading":307,"on_ground":false},{"icao24":"48d852","callsign":"PLF283","country":"Poland","lat":50.049554,"lon":19.484746,"altitude":1127.76,"velocity":111.634348,"heading":115,"on_ground":false},{"icao24":"48d82f","callsign":"PLF111","country":"Poland","lat":50.476076,"lon":20.133842,"altitude":3352.8,"velocity":92.59992,"heading":24.26,"on_ground":false}]}