{"timestamp":1775943923,"count":3,"aircraft":[{"icao24":"ae07f5","callsign":"RCH1845","country":"USA","lat":49.838903,"lon":12.34685,"altitude":10972.800000000001,"velocity":216.580924,"heading":277,"on_ground":false},{"icao24":"ae2fa3","callsign":"RCH168","country":"USA","lat":49.66971,"lon":14.371286,"altitude":11582.400000000001,"velocity":208.864264,"heading":287.93,"on_ground":false},{"icao24":"ae0800","callsign":"RCH1884","country":"USA","lat":48.943925,"lon":17.473318,"altitude":10972.800000000001,"velocity":186.22872800000002,"heading":297,"on_ground":false}]}