{"timestamp":1776349804,"count":4,"aircraft":[{"icao24":"3f447a","callsign":"PRIMR41","country":"Germany","lat":53.908493,"lon":12.024222,"altitude":6088.38,"velocity":183.7593968,"heading":20.31,"on_ground":false},{"icao24":"3b75f7","callsign":"FAF6526","country":"France","lat":49.630411,"lon":12.824163,"altitude":7010.400000000001,"velocity":163.33597,"heading":44.11,"on_ground":false},{"icao24":"3b75f1","callsign":"FAF6525","country":"France","lat":49.864838,"lon":13.174559,"altitude":3741.42,"velocity":129.12544400000002,"heading":44.19,"on_ground":false},{"icao24":"48d8e0","callsign":"FENIX06","country":"Poland","lat":52.341599,"lon":18.049611,"altitude":2682.2400000000002,"velocity":70.993272,"heading":282,"on_ground":false}]}