{"timestamp":1775042722,"count":10,"aircraft":[{"icao24":"3f7b3c","callsign":"GAF602","country":"Germany","lat":52.555298,"lon":13.006287,"altitude":3429,"velocity":155.362088,"heading":90.76,"on_ground":false},{"icao24":"3ea048","callsign":"GAF191","country":"Germany","lat":52.366938,"lon":13.500804,"altitude":null,"velocity":1.1317768000000001,"heading":null,"on_ground":true},{"icao24":"ae1456","callsign":"RCH1846","country":"USA","lat":49.495504,"lon":15.381417,"altitude":11582.400000000001,"velocity":239.21646,"heading":291,"on_ground":false},{"icao24":"3f43e6","callsign":"GAF124","country":"Germany","lat":50.437225,"lon":15.871413,"altitude":8831.58,"velocity":216.2722576,"heading":310.85,"on_ground":false},{"icao24":"3f4252","callsign":"GAFR71C","country":"Germany","lat":50.141499,"lon":16.2915,"altitude":8503.92,"velocity":268.025324,"heading":322,"on_ground":false},{"icao24":"ae4e0d","callsign":"HKY771","country":"USA","lat":48.696336,"lon":17.32198,"altitude":8229.6,"velocity":143.015432,"heading":118,"on_ground":false},{"icao24":"3b77ac","callsign":"CTM009","country":"France","lat":52.194214,"lon":18.272629,"altitude":10447.02,"velocity":222.29125240000002,"heading":78.25,"on_ground":false},{"icao24":"48d980","callsign":"PLF110","country":"Poland","lat":53.98798,"lon":18.302738,"altitude":3208.02,"velocity":158.9117516,"heading":328.37,"on_ground":false},{"icao24":"33fff0","callsign":"IAM4616","country":"Italy","lat":51.560188,"lon":21.271057,"altitude":7315.200000000001,"velocity":151.19509159999998,"heading":35.58,"on_ground":false},{"icao24":"4a81f9","callsign":"SVF680","country":"Sweden","lat":50.189854,"lon":22.489316,"altitude":13114.02,"velocity":233.557576,"heading":17.05,"on_ground":false}]}